README.md
setup.cfg
setup.py
news_fetch.egg-info/PKG-INFO
news_fetch.egg-info/SOURCES.txt
news_fetch.egg-info/dependency_links.txt
news_fetch.egg-info/requires.txt
news_fetch.egg-info/top_level.txt
newsfetch/__init__.py
newsfetch/news.py
newsfetch/utils.py