Metadata-Version: 2.1
Name: news-fetch
Version: 0.2.1
Summary: news-fetch is an open source easy-to-use news extractor and basic nlp (cleaning_text, keywords, summary) comes handy that just works
Home-page: https://santhoshse7en.github.io/news-fetch/
Author: M Santhosh Kumar
Author-email: santhoshse7en@gmail.com
License: UNKNOWN
Keywords: Newspaper,news-fetch,without-api,google_scraper,news_scraper,bs4,lxml,news-crawler,news-extractor,crawler,extractor,news,news-websites,elasticsearch,json,python,nlp,data-gathering,news-archive,news-articles,commoncrawl,extract-articles,extract-information,news-scraper,spacy
Platform: UNKNOWN
Classifier: Development Status :: 4 - Beta
Classifier: Intended Audience :: End Users/Desktop
Classifier: Intended Audience :: Developers
Classifier: Intended Audience :: System Administrators
Classifier: License :: OSI Approved :: MIT License
Classifier: Operating System :: OS Independent
Classifier: Programming Language :: Python
Classifier: Topic :: Communications :: Email
Classifier: Topic :: Office/Business
Classifier: Topic :: Software Development :: Bug Tracking
